accentdatabase/__init__.py
accentdatabase/base.py
accentdatabase/config.py
accentdatabase/engine.py
accentdatabase/mixins.py
accentdatabase/operations.py
accentdatabase/session.py
accentdatabase/testing.py
accentdatabase-0.0.22.dist-info/METADATA
accentdatabase-0.0.22.dist-info/WHEEL
accentdatabase-0.0.22.dist-info/licenses/LICENSE
accentdatabase-0.0.22.dist-info/RECORD
