Metadata-Version: 2.4
Name: accentdatabase
Version: 0.0.22
Dynamic: Summary
Project-URL: Homepage, https://github.com/accentdesign/accentdatabase
Author-email: Accent Design Group Ltd <support@accentdesign.co.uk>
License: The MIT License (MIT)
License-File: LICENSE
Classifier: License :: OSI Approved :: MIT License
Classifier: Programming Language :: Python
Classifier: Programming Language :: Python :: 3
Requires-Python: >=3.9
Requires-Dist: pydantic-settings<2.9.0,>=2.0.1
Requires-Dist: pydantic<2.12.0,>=2.0.1
Requires-Dist: sqlalchemy<2.1.0,>=2.0.0
Provides-Extra: alembic
Requires-Dist: alembic; extra == 'alembic'
Provides-Extra: test
Requires-Dist: pytest; extra == 'test'
Requires-Dist: ruff; extra == 'test'
